dlog/__init__.py
dlog/logger.py
json2excel/__init__.py
json2excel/demo_test.py
json2excel/j2e.py
json2excel/handlers/__init__.py
json2excel/handlers/export_handler.py
json2excel/handlers/format_handler.py
json2excel-1.0.4.dist-info/METADATA
json2excel-1.0.4.dist-info/WHEEL
json2excel-1.0.4.dist-info/top_level.txt
json2excel-1.0.4.dist-info/RECORD
