Metadata-Version: 2.1
Name: json2excel
Version: 1.0.4
Summary: Easy transform json 2 excel
Home-page: UNKNOWN
Author: Caturbhuja
Author-email: caturbhuja@foxmail.com
License: MIT
Platform: UNKNOWN
Requires-Dist: openpyxl (==2.6.2)
